model_generate/__init__.py
model_generate-0.0.3.dist-info/METADATA
model_generate-0.0.3.dist-info/WHEEL
model_generate-0.0.3.dist-info/top_level.txt
model_generate-0.0.3.dist-info/RECORD
