Metadata-Version: 2.4
Name: model-generate
Version: 0.0.3
Summary: A unified utility to generate NPU and Hybrid OGA Models
Author-email: AMD <support@amd.com>
Requires-Python: >=3.8
